odoo8_addon_l10n_si-8.0.0.1.3-py2.7-nspkg.pth
odoo_addons/l10n_si/l10n_si_wizard.xml
odoo_addons/l10n_si/__openerp__.py
odoo_addons/l10n_si/__init__.py
odoo_addons/l10n_si/data/res.bank.xml
odoo_addons/l10n_si/data/account.fiscal.position.template.xml
odoo_addons/l10n_si/data/account.fiscal.position.account.template.xml
odoo_addons/l10n_si/data/account.chart.template.xml
odoo_addons/l10n_si/data/account.fiscal.position.tax.template.xml
odoo_addons/l10n_si/data/account.account.template.xml
odoo_addons/l10n_si/data/account.tax.template.xml
odoo_addons/l10n_si/data/account.tax.code.template.xml
odoo_addons/l10n_si/static/description/icon.png
odoo8_addon_l10n_si-8.0.0.1.3.dist-info/top_level.txt
odoo8_addon_l10n_si-8.0.0.1.3.dist-info/WHEEL
odoo8_addon_l10n_si-8.0.0.1.3.dist-info/RECORD
odoo8_addon_l10n_si-8.0.0.1.3.dist-info/metadata.json
odoo8_addon_l10n_si-8.0.0.1.3.dist-info/DESCRIPTION.rst
odoo8_addon_l10n_si-8.0.0.1.3.dist-info/METADATA
odoo8_addon_l10n_si-8.0.0.1.3.dist-info/namespace_packages.txt
