Metadata-Version: 2.0
Name: odoo8-addon-l10n-si
Version: 8.0.0.1.3
Summary: Slovenian account chart, taxes and fiscal forms
Home-page: http://www.mentis.si
Author: UNKNOWN
Author-email: UNKNOWN
License: UNKNOWN
Platform: UNKNOWN
Requires-Dist: odoo (<9.0a,>=8.0a)
Classifier: Programming Language :: Python :: 2.7
Classifier: Framework :: Odoo
